stolos/__init__.py
stolos/api.py
stolos/cli.py
stolos/config.py
stolos/exceptions.py
stolos/shell.py
stolosctl-0.4.5.dist-info/METADATA
stolosctl-0.4.5.dist-info/RECORD
stolosctl-0.4.5.dist-info/WHEEL
stolosctl-0.4.5.dist-info/entry_points.txt
stolosctl-0.4.5.dist-info/top_level.txt
